{
  "courseList1": [
    {
      "id": "1",
      "image": "/static/images/index/建筑设计推广1.jpg",
      "title": "设计核心能力：方案与表达的基础",
      "tag": "培养空间构思、方案创作和图纸表达能力"
    },
    {
      "id": "2",
      "image": "/static/images/index/建筑设计推广2.jpg",
      "title": "技术专业知识：建筑落地的支撑",
      "tag": "聚焦建筑施工、材料、设备等技术环节"
    },
    {
      "id": "3",
      "image": "/static/images/index/建筑设计推广3.jpg",
      "title": "法规标准掌握：设计合规的底线",
      "tag": "涵盖与建筑相关的法律、规范、标准"
    },
    {
      "id": "4",
      "image": "/static/images/index/名师课堂@2x.png",
      "title": "实践综合应用：理论落地的能力",
      "tag": "结合实际项目场景运用"
    }
  ],
  "courseList2": [
    {
      "id": "1",
      "image": "/static/images/index/结构设计推广1.jpg",
      "title": "基础理论知识：结构设计的根",
      "tag": "聚焦数学、力学等核心理论"
    },
    {
      "id": "2",
      "image": "/static/images/index/结构设计推广2.jpg",
      "title": "专业结构设计：不同结构类型的深度掌握",
      "tag": "聚焦各类建筑结构的设计方法"
    },
    {
      "id": "3",
      "image": "/static/images/index/结构设计推广3.jpg",
      "title": "规范标准应用：结构安全的底线",
      "tag": "结构设计必须严格遵循规范，这是保障工程安全的核心"
    },
    {
      "id": "4",
      "image": "/static/images/index/名师课堂@2x.png",
      "title": "实践综合应用：理论落地的能力",
      "tag": "理论与规范结合实际工程场景运用"
    }
  ],
  "courseList3": [
    {
      "id": "1",
      "image": "/static/images/index/给排水设计推广1.jpg",
      "title": "基础理论储备：工程设计的底层支撑",
      "tag": "给排水原理"
    },
    {
      "id": "2",
      "image": "/static/images/index/给排水设计推广2.jpg",
      "title": "专业系统设计：三大核心系统的深度掌握",
      "tag": "聚焦给排水工程的三大核心系统"
    },
    {
      "id": "3",
      "image": "/static/images/index/给排水设计推广3.jpg",
      "title": "规范标准执行：工程合规的核心底线",
      "tag": "给排水工程直接关系水质安全与公共卫生，必须严格遵循规范"
    },
    {
      "id": "4",
      "image": "/static/images/index/名师课堂@2x.png",
      "title": "实践综合应用：理论落地的能力",
      "tag": "理论与规范结合实际工程场景运用"
    }
  ],
  "courseList4": [
    {
      "id": "1",
      "image": "/static/images/index/暖通设计推广1.jpg",
      "title": "基础理论奠基：专业设计的底层逻辑",
      "tag": "暖通空调原理"
    },
    {
      "id": "2",
      "image": "/static/images/index/暖通设计推广2.jpg",
      "title": "专业系统设计：四大核心系统的深度掌握",
      "tag": "聚焦暖通空调的四大核心系统"
    },
    {
      "id": "3",
      "image": "/static/images/index/暖通设计推广3.jpg",
      "title": "规范标准执行：工程合规的核心底线",
      "tag": "暖通设计直接关系建筑能耗、室内环境安全与人体健康，必须严格遵循规范"
    },
    {
      "id": "4",
      "image": "/static/images/index/名师课堂@2x.png",
      "title": "实践综合应用：理论落地的能力",
      "tag": "理论与规范结合实际工程场景运用"
    }
  ],
  "courseList5": [
    {
      "id": "1",
      "image": "/static/images/index/电气设计推广1.jpg",
      "title": "基础理论支撑：电气设计的底层逻辑",
      "tag": "电气原理"
    },
    {
      "id": "2",
      "image": "/static/images/index/电气设计推广2.jpg",
      "title": "专业系统设计：建筑电气核心系统的深度掌握",
      "tag": "聚焦建筑电气的四大核心系统"
    },
    {
      "id": "3",
      "image": "/static/images/index/电气设计推广3.jpg",
      "title": "规范标准执行：电气安全的绝对底线",
      "tag": "电气设计直接关系人身安全与财产安全，必须严格遵循规范"
    },
    {
      "id": "4",
      "image": "/static/images/index/名师课堂@2x.png",
      "title": "实践综合应用：理论落地的能力",
      "tag": "理论与规范结合实际工程场景运用"
    }
  ]
}